snowowl/__init__.py
snowowl/graph/__init__.py
snowowl/graph/edge.py
snowowl/graph/undirected.py
snowowl/graph/vertex.py
snowowl/priorityqueue/__init__.py
snowowl/priorityqueue/heap.py
snowowl-0.0.4.dist-info/LICENSE
snowowl-0.0.4.dist-info/WHEEL
snowowl-0.0.4.dist-info/METADATA
snowowl-0.0.4.dist-info/RECORD
