Metadata-Version: 2.1
Name: snowowl
Version: 0.0.4
Summary: A collection of common data structures
Home-page: https://github.com/greyshell/snowowl
License: GPL-3.0 License
Author: ABHIJIT SINHA
Author-email: grey.shell@gmail.com
Requires-Python: >=3.9.7,<4.0.0
Classifier: License :: Other/Proprietary License
Classifier: Programming Language :: Python :: 3
